pyemd/__init__.py
pyemd/_pot_backend.py
pyemd/emd.cpython-314-x86_64-linux-gnu.so
pyemd/lib/EMD_DEFS.hpp
pyemd/lib/emd_hat.hpp
pyemd/lib/emd_hat_impl.hpp
pyemd/lib/emd_hat_signatures_interface.hpp
pyemd/lib/flow_utils.hpp
pyemd/lib/min_cost_flow.hpp
pyemd-1.1.0.dist-info/LICENSE
pyemd-1.1.0.dist-info/METADATA
pyemd-1.1.0.dist-info/WHEEL
pyemd-1.1.0.dist-info/RECORD
