Metadata-Version: 2.1
Name: pyemd
Version: 1.1.0
Summary: A Python wrapper for Ofir Pele and Michael Werman's implementation of the Earth Mover's Distance.
Author-Email: Will Mayner <wmayner@gmail.com>
License: Copyright (c) 2014-2023 Will Mayner
Classifier: Development Status :: 5 - Production/Stable
Classifier: Intended Audience :: Developers
Classifier: Natural Language :: English
Classifier: License :: OSI Approved :: MIT License
Classifier: Programming Language :: Python :: 3
Project-URL: Homepage, https://github.com/wmayner/pyemd
Project-URL: Bug Tracker, https://github.com/wmayner/pyemd/issues
Requires-Python: >=3.9
Requires-Dist: numpy>=1.15.0
Requires-Dist: pot>=0.9.0
Provides-Extra: test
Requires-Dist: pytest; extra == "test"
Provides-Extra: dist
Requires-Dist: build; extra == "dist"
Requires-Dist: cibuildwheel; extra == "dist"
Requires-Dist: setuptools_scm; extra == "dist"
Requires-Dist: towncrier; extra == "dist"
Requires-Dist: twine; extra == "dist"
Provides-Extra: dev
Requires-Dist: pytest; extra == "dev"
Requires-Dist: build; extra == "dev"
Requires-Dist: cibuildwheel; extra == "dev"
Requires-Dist: setuptools_scm; extra == "dev"
Requires-Dist: towncrier; extra == "dev"
Requires-Dist: twine; extra == "dev"
Requires-Dist: ipython; extra == "dev"
Requires-Dist: meson-python; extra == "dev"
Requires-Dist: ninja; extra == "dev"
Requires-Dist: cython>=3.0; extra == "dev"
